cqlib/VERSION.txt
cqlib/__init__.py
cqlib/_version.py
cqlib/exceptions.py
cqlib/circuits/__init__.py
cqlib/circuits/barrier.py
cqlib/circuits/bit.py
cqlib/circuits/circuit.py
cqlib/circuits/dag.py
cqlib/circuits/instruction.py
cqlib/circuits/instruction_data.py
cqlib/circuits/measure.py
cqlib/circuits/parameter.py
cqlib/circuits/qubit.py
cqlib/circuits/utils.py
cqlib/circuits/commutation/__init__.py
cqlib/circuits/commutation/_gates_commutations.py
cqlib/circuits/commutation/circuit_commutate.py
cqlib/circuits/commutation/commutation.py
cqlib/circuits/gates/__init__.py
cqlib/circuits/gates/gate.py
cqlib/circuits/gates/h.py
cqlib/circuits/gates/i.py
cqlib/circuits/gates/rx.py
cqlib/circuits/gates/rxy.py
cqlib/circuits/gates/ry.py
cqlib/circuits/gates/rz.py
cqlib/circuits/gates/s.py
cqlib/circuits/gates/swap.py
cqlib/circuits/gates/t.py
cqlib/circuits/gates/u.py
cqlib/circuits/gates/x.py
cqlib/circuits/gates/xy.py
cqlib/circuits/gates/y.py
cqlib/circuits/gates/z.py
cqlib/mapping/__init__.py
cqlib/mapping/cir_dg.py
cqlib/mapping/cir_dg_swap_depth_opt.py
cqlib/mapping/front_circuit.py
cqlib/mapping/genetic_swap_depth_opt.py
cqlib/mapping/mapping.py
cqlib/mapping/monte_carlo_tree.py
cqlib/mapping/init_mapping/__init__.py
cqlib/mapping/init_mapping/get_init_map.py
cqlib/mapping/init_mapping/sa_mapping.py
cqlib/mapping/init_mapping/subgraph_isomorphism_mapping.py
cqlib/mapping/init_mapping/FiDLS/FiDLS_inimap.py
cqlib/mapping/init_mapping/FiDLS/FiDLS_run.py
cqlib/mapping/init_mapping/FiDLS/__init__.py
cqlib/mapping/init_mapping/FiDLS/ag.py
cqlib/mapping/init_mapping/FiDLS/fidls_d.py
cqlib/mapping/init_mapping/FiDLS/fidls_g.py
cqlib/mapping/init_mapping/FiDLS/inimap.py
cqlib/mapping/init_mapping/FiDLS/maps.py
cqlib/mapping/init_mapping/FiDLS/sqatest0.py
cqlib/mapping/init_mapping/FiDLS/utils.py
cqlib/mapping/init_mapping/FiDLS/vfs.py
cqlib/mapping/init_mapping/FiDLS/vfstest.py
cqlib/quantum_platform/__init__.py
cqlib-1.3.5.dist-info/METADATA
cqlib-1.3.5.dist-info/WHEEL
cqlib-1.3.5.dist-info/top_level.txt
cqlib-1.3.5.dist-info/RECORD
cqlib-1.3.5.dist-info/licenses/LICENSE
