Metadata-Version: 2.4
Name: cqlib
Version: 1.3.5
Summary: China Quantum Library
Author-email: China Telecom Quantum Group Quantum Computing Team <tianyan@chinatelecom.cn>, QuantumCTek <service@quantumctek-cloud.com>
License: Apache 2.0
Project-URL: Homepage, https://qc.zdxlz.com/
Project-URL: Documentation, https://cqlib.readthedocs.io/
Project-URL: Repository, https://gitee.com/cq-lib/cqlib
Project-URL: Issues, https://gitee.com/cq-lib/cqlib/issues
Keywords: cqlib,quantum circuit,quantum computing,quantum programming language,quantum,sdk
Classifier: Environment :: Console
Classifier: License :: OSI Approved :: Apache Software License
Classifier: Operating System :: MacOS
Classifier: Operating System :: Microsoft :: Windows
Classifier: Operating System :: POSIX :: Linux
Classifier: Programming Language :: Python :: 3 :: Only
Classifier: Programming Language :: Python :: 3.10
Classifier: Programming Language :: Python :: 3.11
Classifier: Programming Language :: Python :: 3.12
Classifier: Programming Language :: Python :: 3.13
Classifier: Topic :: Software Development :: Libraries
Requires-Python: >=3.10, <4
License-File: LICENSE
Requires-Dist: matplotlib>=3.7.5
Requires-Dist: networkx>=3.0
Requires-Dist: numpy>=2.1.2
Requires-Dist: requests>=2.31.0
Requires-Dist: sympy>=1.12.0
Requires-Dist: tabulate>=0.9.0
Requires-Dist: openqasm3[parser]>=1.0.0
Requires-Dist: antlr4-python3-runtime>=4.13.2
Requires-Dist: rustworkx>=0.16.0
Provides-Extra: simple-sim
Requires-Dist: torch>=2.0.0; extra == "simple-sim"
Dynamic: license-file
Dynamic: requires-python
